bareasgi_static/__init__.py
bareasgi_static/file_streaming.py
bareasgi_static/py.typed
bareasgi_static/static_files_provider.py
bareasgi_static-4.1.0.dist-info/LICENSE
bareasgi_static-4.1.0.dist-info/WHEEL
bareasgi_static-4.1.0.dist-info/METADATA
bareasgi_static-4.1.0.dist-info/RECORD
