Metadata-Version: 2.1
Name: bareasgi-static
Version: 4.1.0
Summary: Static file support for bareASGI
Home-page: https://github.com/rob-blackbourn/bareASGI-static
License: Apache-2.0
Author: Rob Blackbourn
Author-email: rob.blackbourn@gmail.com
Requires-Python: >=3.8,<4.0
Classifier: License :: OSI Approved :: Apache Software License
Classifier: Programming Language :: Python :: 3
Classifier: Programming Language :: Python :: 3.10
Classifier: Programming Language :: Python :: 3.8
Classifier: Programming Language :: Python :: 3.9
Requires-Dist: aiofiles (>=0.7,<0.8)
Requires-Dist: bareASGI (>=4.0.0,<5.0.0)
Project-URL: Repository, https://github.com/rob-blackbourn/bareASGI-static
